StyleTransferArt/style_transfer.py
StyleTransferArt-1.0.3.dist-info/LICENSE
StyleTransferArt-1.0.3.dist-info/METADATA
StyleTransferArt-1.0.3.dist-info/WHEEL
StyleTransferArt-1.0.3.dist-info/top_level.txt
StyleTransferArt-1.0.3.dist-info/RECORD
