Metadata-Version: 2.1
Name: StyleTransferArt
Version: 1.0.3
Summary: Python Package to compose one image in the style of another image
Home-page: https://iraqprogrammer.wordpress.com/
Author: Falah.G.Saleh
Author-email: falahgs07@gmail.com
License: UNKNOWN
Keywords: Style Transfer,images,dataset images
Platform: UNKNOWN
Classifier: Programming Language :: Python :: 3
Classifier: Programming Language :: Python :: 3.5
Classifier: Programming Language :: Python :: 3.6
Classifier: Programming Language :: Python :: 3.7
Classifier: Programming Language :: Python :: 3.8
Classifier: License :: OSI Approved :: MIT License
Classifier: Operating System :: OS Independent
Requires-Python: >=3.6
Requires-Dist: tensorflow
Requires-Dist: matplotlib
